kosmos/__init__.py
kosmos/attend.py
kosmos/model.py
kosmos/transformer.py
kosmos_2-0.1.0.dist-info/LICENSE
kosmos_2-0.1.0.dist-info/WHEEL
kosmos_2-0.1.0.dist-info/METADATA
kosmos_2-0.1.0.dist-info/RECORD
