Metadata-Version: 2.1
Name: kosmos-2
Version: 0.1.0
Summary: kosmos-2 - Pytorch
Home-page: https://github.com/kyegomez/kosmos-2
License: MIT
Keywords: artificial intelligence,attention mechanism,transformers
Author: Kye Gomez
Author-email: kye@apac.ai
Requires-Python: >=3.6,<4.0
Classifier: License :: OSI Approved :: MIT License
Classifier: Programming Language :: Python :: 3
Classifier: Programming Language :: Python :: 3.6
Classifier: Programming Language :: Python :: 3.7
Classifier: Programming Language :: Python :: 3.8
Classifier: Programming Language :: Python :: 3.9
Classifier: Programming Language :: Python :: 3.10
Classifier: Programming Language :: Python :: 3.11
Requires-Dist: SentencePiece
Requires-Dist: accelerate
Requires-Dist: datasets
Requires-Dist: deepspeed
Requires-Dist: einops
Requires-Dist: flamingo-pytorch
Requires-Dist: lion-pytorch
Requires-Dist: matplotlib
Requires-Dist: numpy
Requires-Dist: torch
Requires-Dist: transformers
